[
  {
    "name": "Depot Paris",
    "coordinates": [
      2.2472902,
      48.8621791
    ],
    "weight": 0
  },
  {
    "name": "st remy en bouzemont st genest",
    "coordinates": [
      4.64925753,
      48.613268494
    ],
    "weight": 1
  },
  {
    "name": "pissy poville",
    "coordinates": [
      1.001895493,
      49.533770701
    ],
    "weight": 1
  },
  {
    "name": "la tombe",
    "coordinates": [
      3.09317412,
      48.386672953
    ],
    "weight": 3
  },
  {
    "name": "chaux des crotenay",
    "coordinates": [
      5.957121204,
      46.66328688
    ],
    "weight": 2
  },
  {
    "name": "arques la bataille",
    "coordinates": [
      1.137815968,
      49.882469559
    ],
    "weight": 3
  },
  {
    "name": "sainville",
    "coordinates": [
      1.881545726,
      48.415502379
    ],
    "weight": 3
  },
  {
    "name": "maisons",
    "coordinates": [
      2.640431656,
      42.929531435
    ],
    "weight": 3
  },
  {
    "name": "herin",
    "coordinates": [
      3.448511285,
      50.358274584
    ],
    "weight": 1
  },
  {
    "name": "rogliano",
    "coordinates": [
      9.426060268,
      42.972127086
    ],
    "weight": 2
  },
  {
    "name": "pihem",
    "coordinates": [
      2.212245781,
      50.675948524
    ],
    "weight": 1
  },
  {
    "name": "trevol",
    "coordinates": [
      3.316073994,
      46.63727968
    ],
    "weight": 1
  },
  {
    "name": "vaux sur lunain",
    "coordinates": [
      2.956878876,
      48.216495181
    ],
    "weight": 1
  },
  {
    "name": "st mard de vaux",
    "coordinates": [
      4.672739168,
      46.813487715
    ],
    "weight": 2
  },
  {
    "name": "auzas",
    "coordinates": [
      0.8943728550000001,
      43.174912217
    ],
    "weight": 3
  },
  {
    "name": "hericourt",
    "coordinates": [
      6.762227749,
      47.569197714
    ],
    "weight": 2
  },
  {
    "name": "fontaine sous preaux",
    "coordinates": [
      1.168889652,
      49.485713543
    ],
    "weight": 2
  },
  {
    "name": "ladon",
    "coordinates": [
      2.526169254,
      48.00947309
    ],
    "weight": 3
  }
]